{
    "constructors": [],
    "externalReferences": [],
    "id": "01pA0000002hkELIAY",
    "innerClasses": [],
    "interfaces": [],
    "key": "01pA0000002hkELIAY",
    "methods": [
        {
            "annotations": [],
            "location": {
                "column": 17,
                "line": 2
            },
            "modifiers": [
                "public"
            ],
            "name": "init",
            "parameters": [],
            "references": [],
            "returnType": "void",
            "type": null
        }
    ],
    "name": "congregationmapController",
    "namespace": "ARCFleet",
    "parentClass": "ARCFleet.territorytemplatecontroller",
    "properties": [],
    "tableDeclaration": {
        "annotations": [],
        "location": {
            "column": 14,
            "line": 1
        },
        "modifiers": [
            "public"
        ],
        "name": "congregationmapController",
        "references": [],
        "type": "congregationmapController"
    },
    "variables": []
}