{
    "constructors": [],
    "externalReferences": [],
    "id": "01pA0000002hWuzIAE",
    "innerClasses": [],
    "interfaces": [],
    "key": "01pA0000002hWuzIAE",
    "methods": [
        {
            "annotations": [],
            "location": {
                "column": 17,
                "line": 14
            },
            "modifiers": [
                "public"
            ],
            "name": "init",
            "parameters": [],
            "references": [],
            "returnType": "void",
            "type": null
        },
        {
            "annotations": [],
            "location": {
                "column": 26,
                "line": 26
            },
            "modifiers": [
                "public"
            ],
            "name": "saveSectors",
            "parameters": [],
            "references": [],
            "returnType": "PageReference",
            "type": null
        },
        {
            "annotations": [],
            "location": {
                "column": 26,
                "line": 50
            },
            "modifiers": [
                "public"
            ],
            "name": "clearBeaconStars",
            "parameters": [],
            "references": [],
            "returnType": "PageReference",
            "type": null
        },
        {
            "annotations": [],
            "location": {
                "column": 26,
                "line": 63
            },
            "modifiers": [
                "public"
            ],
            "name": "expungeOrphanSectors",
            "parameters": [],
            "references": [],
            "returnType": "PageReference",
            "type": null
        }
    ],
    "name": "mapcontroller",
    "namespace": "ARCFleet",
    "parentClass": "",
    "properties": [
        {
            "annotations": [],
            "location": {
                "column": 33,
                "line": 2
            },
            "modifiers": [
                "public"
            ],
            "name": "id",
            "references": [],
            "type": "String"
        },
        {
            "annotations": [],
            "location": {
                "column": 33,
                "line": 3
            },
            "modifiers": [
                "public"
            ],
            "name": "sectors",
            "references": [],
            "type": "LIST"
        },
        {
            "annotations": [],
            "location": {
                "column": 33,
                "line": 4
            },
            "modifiers": [
                "public"
            ],
            "name": "m",
            "references": [],
            "type": "ARCFleet__Map__c"
        },
        {
            "annotations": [],
            "location": {
                "column": 33,
                "line": 5
            },
            "modifiers": [
                "public"
            ],
            "name": "maps",
            "references": [],
            "type": "LIST"
        },
        {
            "annotations": [],
            "location": {
                "column": 33,
                "line": 6
            },
            "modifiers": [
                "public",
                "transient"
            ],
            "name": "sectorJSON",
            "references": [],
            "type": "String"
        },
        {
            "annotations": [],
            "location": {
                "column": 33,
                "line": 7
            },
            "modifiers": [
                "public"
            ],
            "name": "sectorIds",
            "references": [],
            "type": "String"
        },
        {
            "annotations": [],
            "location": {
                "column": 33,
                "line": 8
            },
            "modifiers": [
                "public"
            ],
            "name": "terrainType",
            "references": [],
            "type": "String"
        },
        {
            "annotations": [],
            "location": {
                "column": 33,
                "line": 9
            },
            "modifiers": [
                "public"
            ],
            "name": "beacon",
            "references": [],
            "type": "Integer"
        },
        {
            "annotations": [],
            "location": {
                "column": 33,
                "line": 10
            },
            "modifiers": [
                "public"
            ],
            "name": "isHome",
            "references": [],
            "type": "Boolean"
        },
        {
            "annotations": [],
            "location": {
                "column": 33,
                "line": 11
            },
            "modifiers": [
                "public"
            ],
            "name": "a",
            "references": [],
            "type": "Attachment"
        },
        {
            "annotations": [],
            "location": {
                "column": 33,
                "line": 12
            },
            "modifiers": [
                "public"
            ],
            "name": "darkMatter",
            "references": [],
            "type": "Boolean"
        }
    ],
    "tableDeclaration": {
        "annotations": [],
        "location": {
            "column": 14,
            "line": 1
        },
        "modifiers": [
            "global"
        ],
        "name": "mapcontroller",
        "references": [],
        "type": "mapcontroller"
    },
    "variables": [
        {
            "annotations": [],
            "location": {
                "column": 22,
                "line": 28
            },
            "modifiers": [],
            "name": "sids",
            "references": [],
            "type": "LIST"
        },
        {
            "annotations": [],
            "location": {
                "column": 23,
                "line": 33
            },
            "modifiers": [],
            "name": "s",
            "references": [],
            "type": "ARCFleet__Sector__c"
        },
        {
            "annotations": [],
            "location": {
                "column": 23,
                "line": 44
            },
            "modifiers": [],
            "name": "pr",
            "references": [],
            "type": "PageReference"
        },
        {
            "annotations": [],
            "location": {
                "column": 23,
                "line": 52
            },
            "modifiers": [],
            "name": "s",
            "references": [],
            "type": "ARCFleet__Sector__c"
        },
        {
            "annotations": [],
            "location": {
                "column": 23,
                "line": 57
            },
            "modifiers": [],
            "name": "pr",
            "references": [],
            "type": "PageReference"
        },
        {
            "annotations": [],
            "location": {
                "column": 30,
                "line": 64
            },
            "modifiers": [],
            "name": "DeleteSectors",
            "references": [],
            "type": "LIST"
        },
        {
            "annotations": [],
            "location": {
                "column": 28,
                "line": 65
            },
            "modifiers": [],
            "name": "s",
            "references": [],
            "type": "ARCFleet__Game_Sector__c"
        },
        {
            "annotations": [],
            "location": {
                "column": 23,
                "line": 75
            },
            "modifiers": [],
            "name": "pr",
            "references": [],
            "type": "PageReference"
        }
    ]
}